vstabletop/__init__.py
vstabletop/app.py
vstabletop/config.py
vstabletop/fake_data_generator.py
vstabletop/forms.py
vstabletop/info.py
vstabletop/models.py
vstabletop/myDB.db
vstabletop/paths.py
vstabletop/questions.py
vstabletop/routes_game1.py
vstabletop/routes_game2.py
vstabletop/routes_game3.py
vstabletop/routes_game4.py
vstabletop/routes_game5.py
vstabletop/routes_game6.py
vstabletop/routes_game7.py
vstabletop/routes_game8.py
vstabletop/routes_main.py
vstabletop/routes_scan.py
vstabletop/utils.py
vstabletop/static/calibration.js
vstabletop/static/confetti.js
vstabletop/static/eyeplot.js
vstabletop/static/fabric.js
vstabletop/static/game.js
vstabletop/static/game1.js
vstabletop/static/game2.js
vstabletop/static/game3.js
vstabletop/static/game4.js
vstabletop/static/game5.js
vstabletop/static/game6.js
vstabletop/static/game7.js
vstabletop/static/game8.js
vstabletop/static/index.js
vstabletop/static/placeholder.png
vstabletop/static/scan.js
vstabletop/static/script.js
vstabletop/static/slicer.js
vstabletop/static/data/bw.mat
vstabletop/static/data/game4_phantom.mat
vstabletop/static/data/scan/user_uploaded.seq
vstabletop/static/data/solids/center_ball.npy
vstabletop/static/data/solids/center_ball.stl
vstabletop/static/data/solids/double_cone.npy
vstabletop/static/data/solids/double_cone.stl
vstabletop/static/data/solids/double_cone_rev.npy
vstabletop/static/data/solids/double_cone_rev.stl
vstabletop/static/data/solids/g7_set1_typeA.npy
vstabletop/static/data/solids/g7_set1_typeA.stl
vstabletop/static/data/solids/g7_set1_typeB.npy
vstabletop/static/data/solids/g7_set1_typeB.stl
vstabletop/static/data/solids/g7_set1_typeC.npy
vstabletop/static/data/solids/g7_set1_typeC.stl
vstabletop/static/data/solids/g7_set2_u135_d1.npy
vstabletop/static/data/solids/g7_set2_u135_d1.stl
vstabletop/static/data/solids/g7_set2_u135_d2.npy
vstabletop/static/data/solids/g7_set2_u135_d2.stl
vstabletop/static/data/solids/g7_set2_u135_d3.npy
vs_tabletop-1.0.0.dist-info/LICENSE
vs_tabletop-1.0.0.dist-info/METADATA
vs_tabletop-1.0.0.dist-info/WHEEL
vs_tabletop-1.0.0.dist-info/entry_points.txt
vs_tabletop-1.0.0.dist-info/top_level.txt
vs_tabletop-1.0.0.dist-info/RECORD
