Metadata-Version: 2.1
Name: vs-tabletop
Version: 1.0.0
Summary: Virtual Scanner Tabletop Games
Home-page: https://github.com/imr-framework/vs-tabletop
Author: imr-framework
Author-email: imr.framework2018@gmail.com
License: License :: OSI Approved :: GNU Affero General Public License v3
Classifier: Programming Language :: Python :: 3
Classifier: Programming Language :: Python :: 3.9
Requires-Python: >=3
License-File: LICENSE
Requires-Dist: absl-py (==1.1.0)
Requires-Dist: astor (==0.7.1)
Requires-Dist: astunparse (==1.6.3)
Requires-Dist: bidict (==0.22.0)
Requires-Dist: cachelib (==0.9.0)
Requires-Dist: cachetools (==5.2.0)
Requires-Dist: certifi (==2022.6.15)
Requires-Dist: charset-normalizer (==2.1.0)
Requires-Dist: click (==8.1.3)
Requires-Dist: colorama (==0.4.4)
Requires-Dist: cycler (==0.10.0)
Requires-Dist: dominate (==2.6.0)
Requires-Dist: ellipsinator (==0.2.1)
Requires-Dist: Flask (==2.1.2)
Requires-Dist: Flask-Bootstrap (==3.3.7.1)
Requires-Dist: Flask-Login (==0.6.1)
Requires-Dist: Flask-Session (==0.4.0)
Requires-Dist: Flask-SocketIO (==5.2.0)
Requires-Dist: Flask-SQLAlchemy (==2.5.1)
Requires-Dist: Flask-WTF (==1.0.1)
Requires-Dist: flatbuffers (==1.12)
Requires-Dist: fonttools (==4.33.3)
Requires-Dist: gast (==0.2.2)
Requires-Dist: google-auth (==2.9.0)
Requires-Dist: google-auth-oauthlib (==0.4.6)
Requires-Dist: google-pasta (==0.2.0)
Requires-Dist: greenlet (==1.1.2)
Requires-Dist: grpcio (==1.47.0)
Requires-Dist: gunicorn (==20.1.0)
Requires-Dist: h11 (==0.13.0)
Requires-Dist: h5py (==3.7.0)
Requires-Dist: idna (==3.3)
Requires-Dist: imageio (==2.19.3)
Requires-Dist: importlib-metadata (==4.11.4)
Requires-Dist: itsdangerous (==2.1.2)
Requires-Dist: Jinja2 (==3.1.2)
Requires-Dist: keras (==2.9.0)
Requires-Dist: Keras-Applications (==1.0.8)
Requires-Dist: Keras-Preprocessing (==1.1.2)
Requires-Dist: kiwisolver (==1.0.1)
Requires-Dist: libclang (==14.0.1)
Requires-Dist: Markdown (==3.1)
Requires-Dist: MarkupSafe (==2.1.1)
Requires-Dist: matplotlib (==3.5.2)
Requires-Dist: mock (==2.0.0)
Requires-Dist: networkx (==2.8.4)
Requires-Dist: nibabel (==2.4.0)
Requires-Dist: numpy (==1.22.4)
Requires-Dist: numpy-stl (==2.17.1)
Requires-Dist: oauthlib (==3.2.0)
Requires-Dist: opencv-python (==4.6.0.66)
Requires-Dist: opt-einsum (==3.3.0)
Requires-Dist: packaging (==21.3)
Requires-Dist: pandas (==1.4.2)
Requires-Dist: pbr (==5.1.3)
Requires-Dist: phantominator (==0.6.4)
Requires-Dist: Pillow (==9.2.0)
Requires-Dist: plotly (==5.9.0)
Requires-Dist: protobuf (==3.19.4)
Requires-Dist: psycopg2 (==2.9.3)
Requires-Dist: pyasn1 (==0.4.8)
Requires-Dist: pyasn1-modules (==0.2.8)
Requires-Dist: pydicom (==1.2.2)
Requires-Dist: pymesh (==1.0.2)
Requires-Dist: pyparsing (==2.3.1)
Requires-Dist: pypulseq (==1.3.1.post1)
Requires-Dist: python-dateutil (==2.8.2)
Requires-Dist: python-engineio (==4.3.3)
Requires-Dist: python-socketio (==5.7.0)
Requires-Dist: python-utils (==3.3.3)
Requires-Dist: pytz (==2022.1)
Requires-Dist: PyWavelets (==1.3.0)
Requires-Dist: PyYAML (==5.1)
Requires-Dist: requests (==2.28.1)
Requires-Dist: requests-oauthlib (==1.3.1)
Requires-Dist: rsa (==4.8)
Requires-Dist: scikit-image (==0.19.3)
Requires-Dist: scipy (==1.8.1)
Requires-Dist: selenium (==3.141.0)
Requires-Dist: simple-websocket (==0.5.2)
Requires-Dist: six (==1.16.0)
Requires-Dist: SQLAlchemy (==1.4.37)
Requires-Dist: ssfp (==1.0.0)
Requires-Dist: stl-to-voxel (==0.9.2)
Requires-Dist: tenacity (==8.0.1)
Requires-Dist: tensorboard (==2.9.1)
Requires-Dist: tensorboard-data-server (==0.6.1)
Requires-Dist: tensorboard-plugin-wit (==1.8.1)
Requires-Dist: termcolor (==1.1.0)
Requires-Dist: tifffile (==2022.5.4)
Requires-Dist: tqdm (==4.64.0)
Requires-Dist: typing-extensions (==4.3.0)
Requires-Dist: urllib3 (==1.26.9)
Requires-Dist: virtual-scanner (==2.0.0.post5)
Requires-Dist: visitor (==0.1.3)
Requires-Dist: Werkzeug (==2.1.2)
Requires-Dist: wrapt (==1.14.1)
Requires-Dist: wsproto (==1.1.0)
Requires-Dist: WTForms (==3.0.1)
Requires-Dist: zipp (==3.8.0)
